Workbook

Sheet 资产&负债结构分析
D2: 2023 | E2: 2022 | F2: 2021
B3: 项目
A4: 流动资产 | B4: 货币资金 | D4: ='(经营性&金融性)资产&负债结构分析'!C4 -> 0 | E4: ='(经营性&金融性)资产&负债结构分析'!D4 -> 0 | F4: ='(经营性&金融性)资产&负债结构分析'!E4 -> 0
A5: 流动资产 | B5: 应收账款 | D5: ='(经营性&金融性)资产&负债结构分析'!C7 -> 0 | E5: ='(经营性&金融性)资产&负债结构分析'!D7 -> 0 | F5: ='(经营性&金融性)资产&负债结构分析'!E7 -> 0
A6: 流动资产 | B6: 存货 | D6: ='(经营性&金融性)资产&负债结构分析'!C9 -> 0 | E6: ='(经营性&金融性)资产&负债结构分析'!D9 -> 0 | F6: ='(经营性&金融性)资产&负债结构分析'!E9 -> 0
A9: 非流动资产 | B9: 固定资产 | D9: ='(经营性&金融性)资产&负债结构分析'!C5 -> 0 | E9: ='(经营性&金融性)资产&负债结构分析'!D5 -> 0 | F9: ='(经营性&金融性)资产&负债结构分析'!E5 -> 0

Sheet (经营性&金融性)资产&负债结构分析
C2: 2023 | D2: 2022 | E2: 2021 | H2: 项目 | I2: 2023 | J2: 2022 | K2: 2021
B3: 项目 | H3: 项目
A4: 经营性资产 | B4: 货币资金 | C4: 577212000000 | D4: 613737000000 | E4: 535067000000 | G4: 经营性负债 | H4: 应付票据
A5: 经营性资产 | B5: 固定资产 | C5: 47412000000 | D5: 49941000000 | E5: 45823000000 | G5: 经营性负债 | H5: 应付账款 | I5: 8858000000 | J5: 10349000000 | K5: 6663000000
A6: 经营性资产 | B6: 应收票据 | G6: 经营性负债 | H6: 预收款项
A7: 经营性资产 | B7: 应收账款 | C7: 35636000000 | D7: 36118000000 | E7: 26628000000 | G7: 经营性负债 | H7: 应付职工薪酬 | I7: 49771000000 | J7: 47723000000 | K7: 45759000000
A8: 经营性资产 | B8: 预付款项 | G8: 经营性负债 | H8: 应交税费
A9: 经营性资产 | B9: 存货 | G9: 经营性负债 | H9: 合同负债 | I9: 4159801000000 | J9: 3671177000000
A10: 经营性资产 | B10: 无形资产 | C10: 32613000000 | D10: 33459000000 | E10: 29638000000 | G10: 经营性负债 | H10: 递延所得税负债 | I10: 14148000000 | J10: 14217000000 | K10: 13605000000
A11: 金融性资产 （投资性资产） | B11: 交易性金融资产 | C11: 1803047000000 | D11: 1640519000000 | E11: 1426677000000 | G11: 经营性负债 | H11: 递延收益-非流动负债
A12: 金融性资产 （投资性资产） | B12: 长期股权投资 | C12: 258877000000 | D12: 280793000000 | E12: 284061000000 | G12: 金融性负债 | H12: 应付利息
A13: 金融性资产 （投资性资产） | B13: 持有至到期投资 | G13: 金融性负债 | H13: 应付股利
A14: 金融性资产 （投资性资产） | B14: 投资性房地产 | C14: 143755000000 | D14: 136655000000 | E14: 101690000000 | G14: 金融性负债 | H14: 应付债券 | I14: 964007000000 | J14: 931098000000 | K14: 1097523000000
A15: 金融性资产 （投资性资产） | B15: 长期应收款 | C15: 180674000000 | D15: 186858000000 | E15: 200701000000 | G15: 金融性负债 | H15: 交易性金融负债 | I15: 48619000000 | J15: 84659000000 | K15: 57376000000
A16: 金融性资产 （投资性资产） | B16: 应收利息 | G16: 金融性负债 | H16: 长期应付款合计
A17: 金融性资产 （投资性资产） | B17: 应收股利 | G17: 金融性负债 | H17: 长期借款 | I17: 135161000000 | J17: 151539000000 | K17: 171682000000
A18: 金融性资产 （投资性资产） | B18: 递延所得税资产 | C18: 101337000000 | D18: 89321000000 | E18: 65360000000 | G18: 金融性负债 | H18: 短期借款 | I18: 93322000000 | J18: 121945000000 | K18: 116102000000
A19: 金融性资产 （投资性资产） | B19: 一年内到期的非流动资产 | G19: 金融性负债 | H19: 一年内到期的非流动负债
A20: 金融性资产 （投资性资产） | B20: 其他非流动资产 | H20: 负债合计 | I20: 10354453000000 | J20: 9823944000000 | K20: 9064303000000
B21: 资产合计 | C21: 11583417000000 | D21: 11009940000000 | E21: 10142026000000 | H21: 股东权益合计 | I21: 1228964000000 | J21: 1185996000000 | K21: 1077723000000
A22: 资产比率 | B22: 经营性资产占总资产比率 | C22: =IF(C21=0,0,SUM(C4:C10)/C21) -> 0 | D22: =IF(D21=0,0,SUM(D4:D10)/D21) -> 0 | E22: =IF(E21=0,0,SUM(E4:E10)/E21) -> 0 | G22: 负债比率 | H22: 经营性负债占总负债比率 | I22: =IF(I20=0,0,SUM(I4:I11)/I20) -> 0 | J22: =IF(J20=0,0,SUM(J4:J11)/J20) -> 0 | K22: =IF(K20=0,0,SUM(K4:K11)/K20) -> 0
A23: 资产比率 | B23: 金融性资产占总资产比率 | C23: =IF(C21=0,0,SUM(C11:C19)/C21) -> 0 | D23: =IF(D21=0,0,SUM(D11:D19)/D21) -> 0 | E23: =IF(E21=0,0,SUM(E11:E19)/E21) -> 0 | G23: 负债比率 | H23: 金融性负债占总负债比率 | I23: =IF(I20=0,0,SUM(I12:I19)/I20) -> 0 | J23: =IF(J20=0,0,SUM(J12:J19)/J20) -> 0 | K23: =IF(K20=0,0,SUM(K12:K19)/K20) -> 0

Sheet 利润&现金流结构分析
B2: 项目 | C2: 2023 | D2: 2022 | E2: 2021 | I2: 2023 | J2: 2022 | K2: 2021 | N2: 分项 | O2: 2023 | P2: 2022 | Q2: 2021
B3: 营业总收入 | C3: 913789000000 | D3: 880355000000 | E3: 1180444000000 | G3: 经营现金流 | N3: 营业收入 | O3: =C3 -> 0 | P3: =D3 -> 0 | Q3: =E3 -> 0
B4: 营业成本 | C4: 0 | D4: 0 | E4: 0 | H4: 经营活动产生的现金流量净额 | I4: 360403000000 | J4: 476776000000 | K4: 90116000000 | N4: 资本性支出 | O4: =I5 -> 0 | P4: =J5 -> 0 | Q4: =K5 -> 0
B5: 营业总成本 | C5: 792936000000 | D5: 737516000000 | E5: 1040759000000 | G5: 投资现金流 | H5: 资本性支出 | I5: 7810000000 | J5: 8871000000 | K5: 12186000000 | N5: 核心利润 | O5: =C21 -> 0 | P5: =D21 -> 0 | Q5: =E21 -> 0
B6: 税金及附加 | C6: 3665000000 | D6: 3414000000 | E6: 4570000000 | H6: 投资支付的现金 | I6: 0 | J6: 0 | K6: 0 | N6: 持续经营净利润 | O6: =C18 -> 0 | P6: =D18 -> 0 | Q6: =E18 -> 0
B7: 销售费用 | C7: 0 | D7: 0 | E7: 0 | H7: 投资活动产生的现金流量净额 | I7: -104001000000 | J7: -215760000000 | K7: 27933000000
B8: 管理费用 | C8: 80212000000 | D8: 76401000000 | E8: 172597000000 | G8: 筹资现金流
B9: 研发费用 | C9: 0 | D9: 0 | E9: 0 | H9: 吸收投资收到的现金 | I9: 2999000000 | J9: 3104000000 | K9: 14383000000
B10: 财务费用 | C10: 0 | D10: 0 | E10: 0 | H10: 取得借款收到的现金 | I10: 107295000000 | J10: 186022000000 | K10: 197965000000
B11: 资产减值损失 | C11: 0 | D11: 0 | E11: 0 | H11: 偿还债务支付的现金 | I11: 1202227000000 | J11: 1206226000000 | K11: 1335187000000
B12: 信用减值损失 | C12: 77744000000 | D12: 80553000000 | E12: 90494000000 | H12: 分配股利、利润或偿付利息支付的现金 | I12: 73087000000 | J12: 77800000000 | K12: 92829000000
B13: 其他收益 | C13: 2560000000 | D13: 2994000000 | E13: 2984000000 | H13: 支付其他与筹资活动有关的现金 | I13: 0 | J13: 0 | K13: 0
B14: 投资收益 | C14: 36891000000 | D14: 38612000000 | E14: 103378000000 | H14: 筹资活动产生的现金流量净额 | I14: -222056000000 | J14: -230873000000 | K14: -136412000000
B15: 公允价值变动收益 | C15: -9039000000 | D15: -36936000000 | E15: -22613000000 | G15: 自由现金流 | H15: 自由现金流 | I15: =I4-I5 -> 0 | J15: =J4-J5 -> 0 | K15: =K4-K5 -> 0
B16: 资产处置收益 | C16: 563000000 | D16: 311000000 | E16: 14000000 | F16: DCF估值 | G16: 基准FCF(最近一年) | H16: =I15 -> 0
B17: 营业外收入 | C17: 816000000 | D17: 359000000 | E17: 579000000 | F17: DCF估值 | G17: 折现率(r) | H17: 0.08
B18: 营业外支出 | C18: 1552000000 | D18: 863000000 | E18: 684000000 | F18: DCF估值 | G18: 永续年金增长率(g) | H18: 0.04
B19: 持续经营净利润 | C19: 109274000000 | D19: 134817000000 | E19: 121802000000 | F19: DCF估值 | G19: FCF增长率(G) | H19: =IF(OR(K15=0,K15<0,I15<0),0.1,MIN(0.15,MAX(-0.1,POWER(I15/K15,1/2)-1))) -> 0
B20: 毛利 | C20: =C3-C4 -> 0 | D20: =D3-D4 -> 0 | E20: =E3-E4 -> 0 | F20: DCF估值 | G20: 总股本 | H20: 18210000000
B21: 毛利率 | C21: =IF(C3=0,0,C20/C3) -> 0 | D21: =IF(D3=0,0,D20/D3) -> 0 | E21: =IF(E3=0,0,E20/E3) -> 0 | F21: DCF估值 | G21: 第一年价值 | H21: =H16*(1+H19)/POWER(1+H17,1) -> 0
B22: 核心利润 | C22: =C20-C6-C7-C8-C9-C10 -> 0 | D22: =D20-D6-D7-D8-D9-D10 -> 0 | E22: =E20-E6-E7-E8-E9-E10 -> 0 | F22: DCF估值 | G22: 第二年价值 | H22: =H16*POWER(1+H19,2)/POWER(1+H17,2) -> 0
B23: 核心利润率 | C23: =IF(C3=0,0,C22/C3) -> 0 | D23: =IF(D3=0,0,D22/D3) -> 0 | E23: =IF(E3=0,0,E22/E3) -> 0 | F23: DCF估值 | G23: 第三年价值 | H23: =H16*POWER(1+H19,3)/POWER(1+H17,3) -> 0
B24: 核心利润获现率 | C24: =IF(C22=0,0,I4/C22) -> 0 | D24: =IF(D22=0,0,J4/D22) -> 0 | E24: =IF(E22=0,0,K4/E22) -> 0 | F24: DCF估值 | G24: 永续年金价值 | H24: =(H16*POWER(1+H19,3)*(1+H18))/(H17-H18)/POWER(1+H17,3) -> 0
B25: 销售费用率 | C25: =IF(C3=0,0,C7/C3) -> 0 | D25: =IF(D3=0,0,D7/D3) -> 0 | E25: =IF(E3=0,0,E7/E3) -> 0 | F25: DCF估值 | G25: 永续经营三年后DCF价值 | H25: =SUM(H21:H24) -> 0
B26: 管理费用率 | C26: =IF(C3=0,0,C8/C3) -> 0 | D26: =IF(D3=0,0,D8/D3) -> 0 | E26: =IF(E3=0,0,E8/E3) -> 0 | F26: DCF估值 | G26: 永续经营3年后企业股价 | H26: =H25/H20 -> 0
B27: 营业外收入占比 | C27: =IF(C3=0,0,C17/C3) -> 0 | D27: =IF(D3=0,0,D17/D3) -> 0 | E27: =IF(E3=0,0,E17/E3) -> 0
B28: 净利润营收占比 | C28: =IF(C3=0,0,C19/C3) -> 0 | D28: =IF(D3=0,0,D19/D3) -> 0 | E28: =IF(E3=0,0,E19/E3) -> 0 | F28: 唐朝估值 | G28: 净利润增长率 | H28: 0.1
F29: 唐朝估值 | G29: 无风险收益率(低估区域) | H29: 0.04 | J29: =1/H29 -> 0
F30: 唐朝估值 | G30: 无风险收益率(高估区域) | H30: 0.02 | J30: =1/H30 -> 0
F31: 唐朝估值 | G31: 低估买入点 | H31: =(C19*POWER(1+H28,3))*J29 -> 0 | I31: =H31/H20 -> 0
F32: 唐朝估值 | G32: 再打个7折 | H32: =H31*0.7 -> 0 | I32: =H32/H20 -> 0
F33: 唐朝估值 | G33: 高估卖出点 | H33: =(C19*POWER(1+H28,3))*J30 -> 0 | I33: =H33/H20 -> 0
F36: 杠杆分析 | G36: 2023 | H36: 2022 | I36: 2021
F37: 经营杠杆(DOL) | G37: =IF(AND(D19<>0,D3<>0,ABS((C3/D3)-1)>0.0001),((C19/D19)-1)/((C3/D3)-1),0) -> 0 | H37: =IF(AND(E19<>0,E3<>0,ABS((D3/E3)-1)>0.0001),((D19/E19)-1)/((D3/E3)-1),0) -> 0 | I37: -
F38: 财务杠杆(DFL) | G38: =IF(AND(C19<>0,(C19-C10)<>0),C19/(C19-C10),1) -> 0 | H38: =IF(AND(D19<>0,(D19-D10)<>0),D19/(D19-D10),1) -> 0 | I38: =IF(AND(E19<>0,(E19-E10)<>0),E19/(E19-E10),1) -> 0
F39: 总杠杆(DTL) | G39: =G37*G38 -> 0 | H39: =H37*H38 -> 0 | I39: =I37*I38 -> 0

Sheet 综合实力分析
D3: 2023 | E3: 2022 | F3: 2021
A4: 综合实力分析 | B4: 项目
A5: 盈利能力 | B5: ROE(净资产收益率) | D5: =IF('(经营性&金融性)资产&负债结构分析'!I21=0,0,'利润&现金流结构分析'!C19/'(经营性&金融性)资产&负债结构分析'!I21) -> 0 | E5: =IF('(经营性&金融性)资产&负债结构分析'!J21=0,0,'利润&现金流结构分析'!D19/'(经营性&金融性)资产&负债结构分析'!J21) -> 0 | F5: =IF('(经营性&金融性)资产&负债结构分析'!K21=0,0,'利润&现金流结构分析'!E19/'(经营性&金融性)资产&负债结构分析'!K21) -> 0
A6: 盈利能力 | B6: ROA(总资产收益率) | D6: =IF('(经营性&金融性)资产&负债结构分析'!C21=0,0,'利润&现金流结构分析'!C19/'(经营性&金融性)资产&负债结构分析'!C21) -> 0 | E6: =IF('(经营性&金融性)资产&负债结构分析'!D21=0,0,'利润&现金流结构分析'!D19/'(经营性&金融性)资产&负债结构分析'!D21) -> 0 | F6: =IF('(经营性&金融性)资产&负债结构分析'!E21=0,0,'利润&现金流结构分析'!E19/'(经营性&金融性)资产&负债结构分析'!E21) -> 0
A8: 综合实力分析 | B8: 货币资金 | D8: ='(经营性&金融性)资产&负债结构分析'!C4 -> 0 | E8: ='(经营性&金融性)资产&负债结构分析'!D4 -> 0 | F8: ='(经营性&金融性)资产&负债结构分析'!E4 -> 0
A9: 综合实力分析 | B9: 存货 | D9: ='(经营性&金融性)资产&负债结构分析'!C9 -> 0 | E9: ='(经营性&金融性)资产&负债结构分析'!D9 -> 0 | F9: ='(经营性&金融性)资产&负债结构分析'!E9 -> 0
A10: 综合实力分析 | B10: 固定资产 | D10: ='(经营性&金融性)资产&负债结构分析'!C5 -> 0 | E10: ='(经营性&金融性)资产&负债结构分析'!D5 -> 0 | F10: ='(经营性&金融性)资产&负债结构分析'!E5 -> 0
A11: 综合实力分析 | B11: 核心利润 | D11: ='利润&现金流结构分析'!C22 -> 0 | E11: ='利润&现金流结构分析'!D22 -> 0 | F11: ='利润&现金流结构分析'!E22 -> 0
A12: 综合实力分析 | B12: 经营活动产生的现金流量净额 | D12: ='利润&现金流结构分析'!I4 -> 0 | E12: ='利润&现金流结构分析'!J4 -> 0 | F12: ='利润&现金流结构分析'!K4 -> 0
A13: 综合实力分析 | B13: 资产总计 | D13: ='(经营性&金融性)资产&负债结构分析'!C21 -> 0 | E13: ='(经营性&金融性)资产&负债结构分析'!D21 -> 0 | F13: ='(经营性&金融性)资产&负债结构分析'!E21 -> 0

Sheet 资产负债表分析视角
A1: 科目 | B1: 2023 | C1: 2022 | D1: 2021
A2: 资产总计 | B2: 11583417000000 | C2: 11009940000000 | D2: 10142026000000
A3: 流动资产合计
A4: 非流动资产合计
A5: 负债合计 | B5: 10354453000000 | C5: 9823944000000 | D5: 9064303000000
A6: 流动负债合计
A7: 非流动负债合计
A8: 所有者权益合计 | B8: 1228964000000 | C8: 1185996000000 | D8: 1077723000000
A9: 货币资金 | B9: 577212000000 | C9: 613737000000 | D9: 535067000000
A10: 应收账款 | B10: 35636000000 | C10: 36118000000 | D10: 26628000000
A11: 存货
A12: 固定资产 | B12: 47412000000 | C12: 49941000000 | D12: 45823000000
A13: 短期借款 | B13: 93322000000 | C13: 121945000000 | D13: 116102000000
A14: 长期借款 | B14: 135161000000 | C14: 151539000000 | D14: 171682000000

Sheet 敏感性分析
A1: 敏感性分析 - 可编辑参数
A3: 参数名称 | B3: 参数值 | C3: 说明
A4: 折现率(r) | B4: 0.08 | C4: DCF估值使用
A5: 永续增长率(g) | B5: 0.04 | C5: DCF估值使用
A6: FCF增长率(G) | B6: -0.1 | C6: DCF估值使用
A7: 净利润增长率 | B7: 0.1 | C7: 唐朝估值使用
A8: 无风险收益率(低估) | B8: 0.04 | C8: 唐朝估值使用
A9: 无风险收益率(高估) | B9: 0.02 | C9: 唐朝估值使用
A11: 基础数据（最近一年）
A12: 数据项 | B12: 数值 | C12: 单位
A13: 自由现金流(FCF) | B13: 352593000000 | C13: 元
A14: 净利润 | B14: 109274000000 | C14: 元
A15: 总股本 | B15: 18210000000 | C15: 股
A17: 估值结果（自动计算）
A18: 估值方法 | B18: 估值结果 | C18: 单位
A19: DCF企业价值 | B19: =B13*(1+B6)/(1+B4)+B13*(1+B6)^2/(1+B4)^2+B13*(1+B6)^3/(1+B4)^3+B13*(1+B6)^3*(1+B5)/(B4-B5)/(1+B4)^3 -> 0 | C19: 元
A20: DCF每股价值 | B20: =B19/B15 -> 0 | C20: 元/股
A21: 唐朝低估价 | B21: =B14*(1+B7)^3/B8/B15 -> 0 | C21: 元/股
A22: 唐朝高估价 | B22: =B14*(1+B7)^3/B9/B15 -> 0 | C22: 元/股
A23: 唐朝安全边际价 | B23: =B21*0.7 -> 0 | C23: 元/股
A25: 使用说明
A26: 1. 直接修改上方参数值，估值结果会自动更新 ✅
A27: 2. 参数说明：
A28: - 折现率：反映投资风险，通常8%-12%
A29: - 永续增长率：长期稳定增长率，通常2%-5%
A30: - FCF增长率：自由现金流增长率
A31: - 净利润增长率：用于唐朝估值法

Sheet 资产负债表分析(优化版)
A1: 【601318.SH】财务分析报告
A2: 工作表: 资产负债表分析 | 生成时间: 2026-02-11 16:15
A4: 【资产】
A5: 分类 | B5: 财务指标 | C5: 2023年 | D5: 2022年 | E5: 2021年 | F5: 单位 | G5: 说明
A6: 流动资产 | B6: 货币资金 | C6: ='(经营性&金融性)资产&负债结构分析'!C4 -> 0 | D6: ='(经营性&金融性)资产&负债结构分析'!D4 -> 0 | E6: ='(经营性&金融性)资产&负债结构分析'!E4 -> 0 | F6: 元 | G6: 企业可随时支配的现金
A7: 流动资产 | B7: 应收账款 | C7: ='(经营性&金融性)资产&负债结构分析'!C7 -> 0 | D7: ='(经营性&金融性)资产&负债结构分析'!D7 -> 0 | E7: ='(经营性&金融性)资产&负债结构分析'!E7 -> 0 | F7: 元 | G7: 应收取的销售款项
A8: 流动资产 | B8: 存货 | C8: ='(经营性&金融性)资产&负债结构分析'!C9 -> 0 | D8: ='(经营性&金融性)资产&负债结构分析'!D9 -> 0 | E8: ='(经营性&金融性)资产&负债结构分析'!E9 -> 0 | F8: 元 | G8: 原材料、产成品等
A9: 非流动资产 | B9: 固定资产 | C9: ='(经营性&金融性)资产&负债结构分析'!C5 -> 0 | D9: ='(经营性&金融性)资产&负债结构分析'!D5 -> 0 | E9: ='(经营性&金融性)资产&负债结构分析'!E5 -> 0 | F9: 元 | G9: 房屋、设备等长期资产
A10: 非流动资产 | B10: 无形资产 | C10: ='(经营性&金融性)资产&负债结构分析'!C10 -> 0 | D10: ='(经营性&金融性)资产&负债结构分析'!D10 -> 0 | E10: ='(经营性&金融性)资产&负债结构分析'!E10 -> 0 | F10: 元 | G10: 专利权、商标权等
A11: 合计 | B11: 资产总计 | C11: ='(经营性&金融性)资产&负债结构分析'!C21 -> 0 | D11: ='(经营性&金融性)资产&负债结构分析'!D21 -> 0 | E11: ='(经营性&金融性)资产&负债结构分析'!E21 -> 0 | F11: 元 | G11: 企业全部资源
A13: 【负债】
A14: 分类 | B14: 财务指标 | C14: 2023年 | D14: 2022年 | E14: 2021年 | F14: 单位 | G14: 说明
A15: 流动负债 | B15: 应付账款 | C15: ='(经营性&金融性)资产&负债结构分析'!I5 -> 0 | D15: ='(经营性&金融性)资产&负债结构分析'!J5 -> 0 | E15: ='(经营性&金融性)资产&负债结构分析'!K5 -> 0 | F15: 元
A16: 流动负债 | B16: 短期借款 | C16: ='(经营性&金融性)资产&负债结构分析'!I18 -> 0 | D16: ='(经营性&金融性)资产&负债结构分析'!J18 -> 0 | E16: ='(经营性&金融性)资产&负债结构分析'!K18 -> 0 | F16: 元
A17: 非流动负债 | B17: 长期借款 | C17: ='(经营性&金融性)资产&负债结构分析'!I17 -> 0 | D17: ='(经营性&金融性)资产&负债结构分析'!J17 -> 0 | E17: ='(经营性&金融性)资产&负债结构分析'!K17 -> 0 | F17: 元
A18: 非流动负债 | B18: 应付债券 | C18: ='(经营性&金融性)资产&负债结构分析'!I14 -> 0 | D18: ='(经营性&金融性)资产&负债结构分析'!J14 -> 0 | E18: ='(经营性&金融性)资产&负债结构分析'!K14 -> 0 | F18: 元
A19: 合计 | B19: 负债合计 | C19: ='(经营性&金融性)资产&负债结构分析'!I20 -> 0 | D19: ='(经营性&金融性)资产&负债结构分析'!J20 -> 0 | E19: ='(经营性&金融性)资产&负债结构分析'!K20 -> 0 | F19: 元 | G19: 企业全部债务
A20: 权益 | B20: 所有者权益合计 | C20: ='(经营性&金融性)资产&负债结构分析'!I21 -> 0 | D20: ='(经营性&金融性)资产&负债结构分析'!J21 -> 0 | E20: ='(经营性&金融性)资产&负债结构分析'!K21 -> 0 | F20: 元 | G20: 净资产
A22: 【结构分析】
A23: 分类 | B23: 财务指标 | C23: 2023年 | D23: 2022年 | E23: 2021年 | F23: 单位 | G23: 说明
A24: 资产结构 | B24: 经营性资产占比 | C24: ='(经营性&金融性)资产&负债结构分析'!C22 -> 0 | D24: ='(经营性&金融性)资产&负债结构分析'!D22 -> 0 | E24: ='(经营性&金融性)资产&负债结构分析'!E22 -> 0 | F24: %
A25: 资产结构 | B25: 金融性资产占比 | C25: ='(经营性&金融性)资产&负债结构分析'!C23 -> 0 | D25: ='(经营性&金融性)资产&负债结构分析'!D23 -> 0 | E25: ='(经营性&金融性)资产&负债结构分析'!E23 -> 0 | F25: %
A26: 负债结构 | B26: 经营性负债占比 | C26: ='(经营性&金融性)资产&负债结构分析'!I22 -> 0 | D26: ='(经营性&金融性)资产&负债结构分析'!J22 -> 0 | E26: ='(经营性&金融性)资产&负债结构分析'!K22 -> 0 | F26: %
A27: 负债结构 | B27: 金融性负债占比 | C27: ='(经营性&金融性)资产&负债结构分析'!I23 -> 0 | D27: ='(经营性&金融性)资产&负债结构分析'!J23 -> 0 | E27: ='(经营性&金融性)资产&负债结构分析'!K23 -> 0 | F27: %

Sheet 利润&现金流分析(优化版)
A1: 【601318.SH】财务分析报告
A2: 工作表: 利润&现金流分析 | 生成时间: 2026-02-11 16:15
A4: 【利润表】
A5: 分类 | B5: 财务指标 | C5: 2023年 | D5: 2022年 | E5: 2021年 | F5: 单位 | G5: 说明
A6: 收入 | B6: 营业总收入 | C6: 913789000000 | D6: 880355000000 | E6: 1180444000000 | F6: 元 | G6: 主营业务收入
A7: 成本 | B7: 营业成本 | C7: 0 | D7: 0 | E7: 0 | F7: 元 | G7: 直接成本
A8: 成本 | B8: 营业总成本 | C8: 792936000000 | D8: 737516000000 | E8: 1040759000000 | F8: 元
A9: 费用 | B9: 税金及附加 | C9: 3665000000 | D9: 3414000000 | E9: 4570000000 | F9: 元
A10: 费用 | B10: 销售费用 | C10: 0 | D10: 0 | E10: 0 | F10: 元 | G10: 销售过程费用
A11: 费用 | B11: 管理费用 | C11: 80212000000 | D11: 76401000000 | E11: 172597000000 | F11: 元 | G11: 管理活动费用
A12: 费用 | B12: 研发费用 | C12: 0 | D12: 0 | E12: 0 | F12: 元
A13: 费用 | B13: 财务费用 | C13: 0 | D13: 0 | E13: 0 | F13: 元 | G13: 利息支出净额
A14: 利润 | B14: 营业利润 | C14: 120853000000 | D14: 142839000000 | E14: 139685000000 | F14: 元
A15: 利润 | B15: 净利润 | C15: 109274000000 | D15: 134817000000 | E15: 121802000000 | F15: 元 | G15: 最终利润
A16: 利润 | B16: 持续经营净利润 | F16: 元 | G16: 扣除非经常性损益
A18: 【财务比率】
A19: 分类 | B19: 财务指标 | C19: 2023年 | D19: 2022年 | E19: 2021年 | F19: 单位 | G19: 说明
A20: 盈利能力 | B20: 毛利率 | C20: 1 | D20: 1 | E20: 1 | F20: % | G20: 产品盈利能力
A21: 盈利能力 | B21: 核心利润率 | C21: 0.1195834 | D21: 0.15313936 | E21: 0.10318321 | F21: %
A22: 盈利能力 | B22: 净利润率 | C22: 0.1195834 | D22: 0.15313936 | E22: 0.10318321 | F22: %
A24: 【杠杆分析】
A25: 分类 | B25: 财务指标 | C25: 2023年 | D25: 2022年 | E25: 2021年 | F25: 单位 | G25: 说明
A26: 杠杆 | B26: 经营杠杆(DOL) | C26: -4.9888074 | D26: -0.42032485 | E26: - | F26: 倍 | G26: >1表示正向放大
A27: 杠杆 | B27: 财务杠杆(DFL) | C27: 1 | D27: 1 | E27: 1 | F27: 倍 | G27: 接近1表示低风险
A28: 杠杆 | B28: 总杠杆(DTL) | C28: -4.9888074 | D28: -0.42032485 | E28: - | F28: 倍 | G28: 综合杠杆效应
A30: 【现金流量表】
A31: 分类 | B31: 财务指标 | C31: 2023年 | D31: 2022年 | E31: 2021年 | F31: 单位 | G31: 说明
A32: 经营活动 | B32: 经营活动产生的现金流量净额 | C32: 360403000000 | D32: 476776000000 | E32: 90116000000 | F32: 元 | G32: 经营现金净额
A33: 投资活动 | B33: 投资活动产生的现金流量净额 | C33: -104001000000 | D33: -215760000000 | E33: 27933000000 | F33: 元
A34: 筹资活动 | B34: 筹资活动产生的现金流量净额 | C34: -222056000000 | D34: -230873000000 | E34: -136412000000 | F34: 元
A35: 资本支出 | B35: 购建固定资产、无形资产和其他长期资产支付的现金 | C35: 7810000000 | D35: 8871000000 | E35: 12186000000 | F35: 元

Sheet 综合实力分析(优化版)
A1: 【601318.SH】财务分析报告
A2: 工作表: 综合实力分析 | 生成时间: 2026-02-11 16:15
A4: 【盈利能力】
A5: 分类 | B5: 财务指标 | C5: 2023年 | D5: 2022年 | E5: 2021年 | F5: 单位 | G5: 说明
A6: 盈利能力 | B6: ROE(净资产收益率) | C6: 0.088915542 | D6: 0.11367408 | E6: 0.11301791 | F6: % | G6: 股东回报率
A7: 盈利能力 | B7: ROA(总资产收益率) | C7: 0.0094336585 | D7: 0.012245026 | E7: 0.012009632 | F7: % | G7: 资产使用效率
A8: 盈利能力 | B8: 净利润率 | C8: 0.1195834 | D8: 0.15313936 | E8: 0.10318321 | F8: %
A9: 盈利能力 | B9: 毛利率 | C9: 1 | D9: 1 | E9: 1 | F9: % | G9: 产品盈利能力
A11: 【偿债能力】
A12: 分类 | B12: 财务指标 | C12: 2023年 | D12: 2022年 | E12: 2021年 | F12: 单位 | G12: 说明
A13: 偿债能力 | B13: 资产负债率 | C13: 0.89390315 | D13: 0.89227952 | E13: 0.89373691 | F13: % | G13: 负债/资产，<60%较安全
A15: 【关键指标】
A16: 分类 | B16: 财务指标 | C16: 2023年 | D16: 2022年 | E16: 2021年 | F16: 单位 | G16: 说明
A17: 资产 | B17: 货币资金 | C17: 577212000000 | D17: 613737000000 | E17: 535067000000 | F17: 元 | G17: 企业可随时支配的现金
A18: 资产 | B18: 存货 | C18: 0 | D18: 0 | E18: 0 | F18: 元 | G18: 原材料、产成品等
A19: 资产 | B19: 固定资产 | C19: 47412000000 | D19: 49941000000 | E19: 45823000000 | F19: 元 | G19: 房屋、设备等长期资产
A20: 资产 | B20: 资产总计 | C20: 11583417000000 | D20: 11009940000000 | E20: 10142026000000 | F20: 元 | G20: 企业全部资源
A21: 利润 | B21: 净利润 | C21: 109274000000 | D21: 134817000000 | E21: 121802000000 | F21: 元 | G21: 最终利润
A22: 现金流 | B22: 经营活动产生的现金流量净额 | C22: 360403000000 | D22: 476776000000 | E22: 90116000000 | F22: 元 | G22: 经营现金净额

Sheet 敏感性分析(优化版)
A1: 【601318.SH】财务分析报告
A2: 工作表: 敏感性分析 | 生成时间: 2026-02-11 16:15
A4: 可编辑参数
A5: 参数名称 | B5: 参数值 | C5: 单位 | D5: 说明
A6: 折现率(r) | B6: 0.08 | C6: %
A7: 永续增长率(g) | B7: 0.04 | C7: %
A8: FCF增长率(G) | B8: -0.1 | C8: %
A9: 净利润增长率 | B9: 0.1 | C9: %
A10: 无风险收益率(低估) | B10: 0.04 | C10: % | D10: 用于计算低估PE倍数
A11: 无风险收益率(高估) | B11: 0.02 | C11: % | D11: 用于计算高估PE倍数
A13: 基础数据（最近一年）
A14: 数据项 | B14: 数值 | C14: 单位 | D14: 说明
A15: 自由现金流(FCF) | B15: 352593000000 | C15: 元 | D15: 经营现金流-资本支出
A16: 净利润 | B16: 109274000000 | C16: 元 | D16: 最终利润
A17: 总股本 | B17: 18210000000 | C17: 股 | D17: 公司发行的股票总数
A19: 估值结果（基于上述参数计算）
A20: 估值方法 | B20: 估值结果 | C20: 单位 | D20: 说明
A21: DCF企业价值 | B21: =B15*(1+B8)/(MAX(B6-B7,0.0001)) -> 0 | C21: 元 | D21: 现金流折现价值
A22: DCF每股价值 | B22: =B21/B17 -> 0 | C22: 元/股 | D22: 企业价值/总股本
A23: 唐朝低估价 | B23: =B16*(1+B9)*(1/MAX(B10,0.0001))/B17 -> 0 | C23: 元/股 | D23: 保守买入价
A24: 唐朝高估价 | B24: =B16*(1+B9)*(1/MAX(B11,0.0001))/B17 -> 0 | C24: 元/股 | D24: 乐观卖出价
A25: 唐朝安全边际价 | B25: =(B23+B24)/2 -> 0 | C25: 元/股
